{"parent":"nova:block_base","textures":{"2":"block/spruce_log_top","1":"block/spruce_log","0":"nova:block/leaves/spruce"},"elements":[{"from":[7.5893307666666665,3.2853333333333334,9.231997433333333],"to":[8.4106641,4.106666666666667,10.053330766666667],"faces":{"north":{"uv":[0.0,0.0,16.0,16.0],"texture":"#0"},"east":{"uv":[0.0,0.0,16.0,16.0],"texture":"#0"},"south":{"uv":[0.0,0.0,16.0,16.0],"texture":"#0"},"west":{"uv":[0.0,0.0,16.0,16.0],"texture":"#0"},"up":{"uv":[0.0,0.0,16.0,16.0],"texture":"#0"},"down":{"uv":[0.0,0.0,16.0,16.0],"texture":"#0"}}},{"from":[5.9466641,1.6426666666666667,7.5893307666666665],"to":[6.767997433333333,2.464,8.4106641],"faces":{"north":{"uv":[0.0,0.0,16.0,16.0],"texture":"#0"},"east":{"uv":[0.0,0.0,16.0,16.0],"texture":"#0"},"south":{"uv":[0.0,0.0,16.0,16.0],"texture":"#0"},"west":{"uv":[0.0,0.0,16.0,16.0],"texture":"#0"},"up":{"uv":[0.0,0.0,16.0,16.0],"texture":"#0"},"down":{"uv":[0.0,0.0,16.0,16.0],"texture":"#0"}}},{"from":[7.5893307666666665,0.0,7.5893307666666665],"to":[8.4106641,0.8213333333333334,8.4106641],"faces":{"north":{"uv":[0.0,0.0,16.0,16.0],"texture":"#1"},"east":{"uv":[0.0,0.0,16.0,16.0],"texture":"#1"},"south":{"uv":[0.0,0.0,16.0,16.0],"texture":"#1"},"west":{"uv":[0.0,0.0,16.0,16.0],"texture":"#1"},"down":{"uv":[0.0,0.0,16.0,16.0],"texture":"#2"}}},{"from":[9.231997433333333,1.6426666666666667,6.767997433333333],"to":[10.053330766666667,2.464,7.5893307666666665],"faces":{"north":{"uv":[0.0,0.0,16.0,16.0],"texture":"#0"},"east":{"uv":[0.0,0.0,16.0,16.0],"texture":"#0"},"south":{"uv":[0.0,0.0,16.0,16.0],"texture":"#0"},"west":{"uv":[0.0,0.0,16.0,16.0],"texture":"#0"},"up":{"uv":[0.0,0.0,16.0,16.0],"texture":"#0"},"down":{"uv":[0.0,0.0,16.0,16.0],"texture":"#0"}}},{"from":[7.5893307666666665,1.6426666666666667,5.9466641],"to":[8.4106641,2.464,6.767997433333333],"faces":{"north":{"uv":[0.0,0.0,16.0,16.0],"texture":"#0"},"east":{"uv":[0.0,0.0,16.0,16.0],"texture":"#0"},"south":{"uv":[0.0,0.0,16.0,16.0],"texture":"#0"},"west":{"uv":[0.0,0.0,16.0,16.0],"texture":"#0"},"up":{"uv":[0.0,0.0,16.0,16.0],"texture":"#0"},"down":{"uv":[0.0,0.0,16.0,16.0],"texture":"#0"}}},{"from":[7.5893307666666665,1.6426666666666667,7.5893307666666665],"to":[8.4106641,2.464,8.4106641],"faces":{"north":{"uv":[0.0,0.0,16.0,16.0],"texture":"#1"},"east":{"uv":[0.0,0.0,16.0,16.0],"texture":"#1"},"south":{"uv":[0.0,0.0,16.0,16.0],"texture":"#1"},"west":{"uv":[0.0,0.0,16.0,16.0],"texture":"#1"}}},{"from":[9.231997433333333,3.2853333333333334,7.5893307666666665],"to":[10.053330766666667,4.106666666666667,8.4106641],"faces":{"north":{"uv":[0.0,0.0,16.0,16.0],"texture":"#0"},"east":{"uv":[0.0,0.0,16.0,16.0],"texture":"#0"},"south":{"uv":[0.0,0.0,16.0,16.0],"texture":"#0"},"west":{"uv":[0.0,0.0,16.0,16.0],"texture":"#0"},"up":{"uv":[0.0,0.0,16.0,16.0],"texture":"#0"},"down":{"uv":[0.0,0.0,16.0,16.0],"texture":"#0"}}},{"from":[6.767997433333333,1.6426666666666667,9.231997433333333],"to":[7.5893307666666665,2.464,10.053330766666667],"faces":{"north":{"uv":[0.0,0.0,16.0,16.0],"texture":"#0"},"east":{"uv":[0.0,0.0,16.0,16.0],"texture":"#0"},"south":{"uv":[0.0,0.0,16.0,16.0],"texture":"#0"},"west":{"uv":[0.0,0.0,16.0,16.0],"texture":"#0"},"up":{"uv":[0.0,0.0,16.0,16.0],"texture":"#0"},"down":{"uv":[0.0,0.0,16.0,16.0],"texture":"#0"}}},{"from":[8.4106641,2.464,7.5893307666666665],"to":[9.231997433333333,3.2853333333333334,8.4106641],"faces":{"north":{"uv":[0.0,0.0,16.0,16.0],"texture":"#0"},"east":{"uv":[0.0,0.0,16.0,16.0],"texture":"#0"},"south":{"uv":[0.0,0.0,16.0,16.0],"texture":"#0"},"up":{"uv":[0.0,0.0,16.0,16.0],"texture":"#0"},"down":{"uv":[0.0,0.0,16.0,16.0],"texture":"#0"}}},{"from":[7.5893307666666665,2.464,8.4106641],"to":[8.4106641,3.2853333333333334,9.231997433333333],"faces":{"east":{"uv":[0.0,0.0,16.0,16.0],"texture":"#0"},"south":{"uv":[0.0,0.0,16.0,16.0],"texture":"#0"},"west":{"uv":[0.0,0.0,16.0,16.0],"texture":"#0"},"up":{"uv":[0.0,0.0,16.0,16.0],"texture":"#0"},"down":{"uv":[0.0,0.0,16.0,16.0],"texture":"#0"}}},{"from":[8.4106641,3.2853333333333334,8.4106641],"to":[9.231997433333333,4.106666666666667,9.231997433333333],"faces":{"north":{"uv":[0.0,0.0,16.0,16.0],"texture":"#0"},"east":{"uv":[0.0,0.0,16.0,16.0],"texture":"#0"},"south":{"uv":[0.0,0.0,16.0,16.0],"texture":"#0"},"west":{"uv":[0.0,0.0,16.0,16.0],"texture":"#0"},"up":{"uv":[0.0,0.0,16.0,16.0],"texture":"#0"},"down":{"uv":[0.0,0.0,16.0,16.0],"texture":"#0"}}},{"from":[8.4106641,1.6426666666666667,5.9466641],"to":[9.231997433333333,2.464,6.767997433333333],"faces":{"north":{"uv":[0.0,0.0,16.0,16.0],"texture":"#0"},"east":{"uv":[0.0,0.0,16.0,16.0],"texture":"#0"},"south":{"uv":[0.0,0.0,16.0,16.0],"texture":"#0"},"west":{"uv":[0.0,0.0,16.0,16.0],"texture":"#0"},"up":{"uv":[0.0,0.0,16.0,16.0],"texture":"#0"},"down":{"uv":[0.0,0.0,16.0,16.0],"texture":"#0"}}},{"from":[8.4106641,1.6426666666666667,7.5893307666666665],"to":[9.231997433333333,2.464,8.4106641],"faces":{"north":{"uv":[0.0,0.0,16.0,16.0],"texture":"#0"},"east":{"uv":[0.0,0.0,16.0,16.0],"texture":"#0"},"south":{"uv":[0.0,0.0,16.0,16.0],"texture":"#0"},"up":{"uv":[0.0,0.0,16.0,16.0],"texture":"#0"},"down":{"uv":[0.0,0.0,16.0,16.0],"texture":"#0"}}},{"from":[7.5893307666666665,1.6426666666666667,8.4106641],"to":[8.4106641,2.464,9.231997433333333],"faces":{"east":{"uv":[0.0,0.0,16.0,16.0],"texture":"#0"},"south":{"uv":[0.0,0.0,16.0,16.0],"texture":"#0"},"west":{"uv":[0.0,0.0,16.0,16.0],"texture":"#0"},"up":{"uv":[0.0,0.0,16.0,16.0],"texture":"#0"},"down":{"uv":[0.0,0.0,16.0,16.0],"texture":"#0"}}},{"from":[9.231997433333333,3.2853333333333334,8.4106641],"to":[10.053330766666667,4.106666666666667,9.231997433333333],"faces":{"north":{"uv":[0.0,0.0,16.0,16.0],"texture":"#0"},"east":{"uv":[0.0,0.0,16.0,16.0],"texture":"#0"},"south":{"uv":[0.0,0.0,16.0,16.0],"texture":"#0"},"west":{"uv":[0.0,0.0,16.0,16.0],"texture":"#0"},"up":{"uv":[0.0,0.0,16.0,16.0],"texture":"#0"},"down":{"uv":[0.0,0.0,16.0,16.0],"texture":"#0"}}},{"from":[5.9466641,1.6426666666666667,8.4106641],"to":[6.767997433333333,2.464,9.231997433333333],"faces":{"north":{"uv":[0.0,0.0,16.0,16.0],"texture":"#0"},"east":{"uv":[0.0,0.0,16.0,16.0],"texture":"#0"},"south":{"uv":[0.0,0.0,16.0,16.0],"texture":"#0"},"west":{"uv":[0.0,0.0,16.0,16.0],"texture":"#0"},"up":{"uv":[0.0,0.0,16.0,16.0],"texture":"#0"},"down":{"uv":[0.0,0.0,16.0,16.0],"texture":"#0"}}},{"from":[8.4106641,3.2853333333333334,9.231997433333333],"to":[9.231997433333333,4.106666666666667,10.053330766666667],"faces":{"north":{"uv":[0.0,0.0,16.0,16.0],"texture":"#0"},"east":{"uv":[0.0,0.0,16.0,16.0],"texture":"#0"},"south":{"uv":[0.0,0.0,16.0,16.0],"texture":"#0"},"west":{"uv":[0.0,0.0,16.0,16.0],"texture":"#0"},"up":{"uv":[0.0,0.0,16.0,16.0],"texture":"#0"},"down":{"uv":[0.0,0.0,16.0,16.0],"texture":"#0"}}},{"from":[9.231997433333333,1.6426666666666667,7.5893307666666665],"to":[10.053330766666667,2.464,8.4106641],"faces":{"north":{"uv":[0.0,0.0,16.0,16.0],"texture":"#0"},"east":{"uv":[0.0,0.0,16.0,16.0],"texture":"#0"},"south":{"uv":[0.0,0.0,16.0,16.0],"texture":"#0"},"west":{"uv":[0.0,0.0,16.0,16.0],"texture":"#0"},"up":{"uv":[0.0,0.0,16.0,16.0],"texture":"#0"},"down":{"uv":[0.0,0.0,16.0,16.0],"texture":"#0"}}},{"from":[7.5893307666666665,0.8213333333333334,7.5893307666666665],"to":[8.4106641,1.6426666666666667,8.4106641],"faces":{"north":{"uv":[0.0,0.0,16.0,16.0],"texture":"#1"},"east":{"uv":[0.0,0.0,16.0,16.0],"texture":"#1"},"south":{"uv":[0.0,0.0,16.0,16.0],"texture":"#1"},"west":{"uv":[0.0,0.0,16.0,16.0],"texture":"#1"}}},{"from":[8.4106641,1.6426666666666667,8.4106641],"to":[9.231997433333333,2.464,9.231997433333333],"faces":{"north":{"uv":[0.0,0.0,16.0,16.0],"texture":"#0"},"east":{"uv":[0.0,0.0,16.0,16.0],"texture":"#0"},"south":{"uv":[0.0,0.0,16.0,16.0],"texture":"#0"},"west":{"uv":[0.0,0.0,16.0,16.0],"texture":"#0"},"up":{"uv":[0.0,0.0,16.0,16.0],"texture":"#0"},"down":{"uv":[0.0,0.0,16.0,16.0],"texture":"#0"}}},{"from":[7.5893307666666665,1.6426666666666667,9.231997433333333],"to":[8.4106641,2.464,10.053330766666667],"faces":{"north":{"uv":[0.0,0.0,16.0,16.0],"texture":"#0"},"east":{"uv":[0.0,0.0,16.0,16.0],"texture":"#0"},"south":{"uv":[0.0,0.0,16.0,16.0],"texture":"#0"},"west":{"uv":[0.0,0.0,16.0,16.0],"texture":"#0"},"up":{"uv":[0.0,0.0,16.0,16.0],"texture":"#0"},"down":{"uv":[0.0,0.0,16.0,16.0],"texture":"#0"}}},{"from":[8.4106641,1.6426666666666667,9.231997433333333],"to":[9.231997433333333,2.464,10.053330766666667],"faces":{"north":{"uv":[0.0,0.0,16.0,16.0],"texture":"#0"},"east":{"uv":[0.0,0.0,16.0,16.0],"texture":"#0"},"south":{"uv":[0.0,0.0,16.0,16.0],"texture":"#0"},"west":{"uv":[0.0,0.0,16.0,16.0],"texture":"#0"},"up":{"uv":[0.0,0.0,16.0,16.0],"texture":"#0"},"down":{"uv":[0.0,0.0,16.0,16.0],"texture":"#0"}}},{"from":[9.231997433333333,1.6426666666666667,8.4106641],"to":[10.053330766666667,2.464,9.231997433333333],"faces":{"north":{"uv":[0.0,0.0,16.0,16.0],"texture":"#0"},"east":{"uv":[0.0,0.0,16.0,16.0],"texture":"#0"},"south":{"uv":[0.0,0.0,16.0,16.0],"texture":"#0"},"west":{"uv":[0.0,0.0,16.0,16.0],"texture":"#0"},"up":{"uv":[0.0,0.0,16.0,16.0],"texture":"#0"},"down":{"uv":[0.0,0.0,16.0,16.0],"texture":"#0"}}},{"from":[6.767997433333333,5.7493333333333325,7.5893307666666665],"to":[7.5893307666666665,6.570666666666667,8.4106641],"faces":{"north":{"uv":[0.0,0.0,16.0,16.0],"texture":"#0"},"south":{"uv":[0.0,0.0,16.0,16.0],"texture":"#0"},"west":{"uv":[0.0,0.0,16.0,16.0],"texture":"#0"},"up":{"uv":[0.0,0.0,16.0,16.0],"texture":"#0"},"down":{"uv":[0.0,0.0,16.0,16.0],"texture":"#0"}}},{"from":[7.5893307666666665,5.7493333333333325,6.767997433333333],"to":[8.4106641,6.570666666666667,7.5893307666666665],"faces":{"north":{"uv":[0.0,0.0,16.0,16.0],"texture":"#0"},"east":{"uv":[0.0,0.0,16.0,16.0],"texture":"#0"},"west":{"uv":[0.0,0.0,16.0,16.0],"texture":"#0"},"up":{"uv":[0.0,0.0,16.0,16.0],"texture":"#0"},"down":{"uv":[0.0,0.0,16.0,16.0],"texture":"#0"}}},{"from":[7.5893307666666665,4.106666666666667,6.767997433333333],"to":[8.4106641,4.928000000000001,7.5893307666666665],"faces":{"north":{"uv":[0.0,0.0,16.0,16.0],"texture":"#0"},"east":{"uv":[0.0,0.0,16.0,16.0],"texture":"#0"},"west":{"uv":[0.0,0.0,16.0,16.0],"texture":"#0"},"up":{"uv":[0.0,0.0,16.0,16.0],"texture":"#0"},"down":{"uv":[0.0,0.0,16.0,16.0],"texture":"#0"}}},{"from":[6.767997433333333,4.106666666666667,7.5893307666666665],"to":[7.5893307666666665,4.928000000000001,8.4106641],"faces":{"north":{"uv":[0.0,0.0,16.0,16.0],"texture":"#0"},"south":{"uv":[0.0,0.0,16.0,16.0],"texture":"#0"},"west":{"uv":[0.0,0.0,16.0,16.0],"texture":"#0"},"up":{"uv":[0.0,0.0,16.0,16.0],"texture":"#0"},"down":{"uv":[0.0,0.0,16.0,16.0],"texture":"#0"}}},{"from":[7.5893307666666665,5.7493333333333325,7.5893307666666665],"to":[8.4106641,6.570666666666667,8.4106641],"faces":{"north":{"uv":[0.0,0.0,16.0,16.0],"texture":"#1"},"east":{"uv":[0.0,0.0,16.0,16.0],"texture":"#1"},"south":{"uv":[0.0,0.0,16.0,16.0],"texture":"#1"},"west":{"uv":[0.0,0.0,16.0,16.0],"texture":"#1"},"up":{"uv":[0.0,0.0,16.0,16.0],"texture":"#2"}}},{"from":[7.5893307666666665,4.106666666666667,7.5893307666666665],"to":[8.4106641,4.928000000000001,8.4106641],"faces":{"north":{"uv":[0.0,0.0,16.0,16.0],"texture":"#1"},"east":{"uv":[0.0,0.0,16.0,16.0],"texture":"#1"},"south":{"uv":[0.0,0.0,16.0,16.0],"texture":"#1"},"west":{"uv":[0.0,0.0,16.0,16.0],"texture":"#1"}}},{"from":[8.4106641,5.7493333333333325,7.5893307666666665],"to":[9.231997433333333,6.570666666666667,8.4106641],"faces":{"north":{"uv":[0.0,0.0,16.0,16.0],"texture":"#0"},"east":{"uv":[0.0,0.0,16.0,16.0],"texture":"#0"},"south":{"uv":[0.0,0.0,16.0,16.0],"texture":"#0"},"up":{"uv":[0.0,0.0,16.0,16.0],"texture":"#0"},"down":{"uv":[0.0,0.0,16.0,16.0],"texture":"#0"}}},{"from":[7.5893307666666665,5.7493333333333325,8.4106641],"to":[8.4106641,6.570666666666667,9.231997433333333],"faces":{"east":{"uv":[0.0,0.0,16.0,16.0],"texture":"#0"},"south":{"uv":[0.0,0.0,16.0,16.0],"texture":"#0"},"west":{"uv":[0.0,0.0,16.0,16.0],"texture":"#0"},"up":{"uv":[0.0,0.0,16.0,16.0],"texture":"#0"},"down":{"uv":[0.0,0.0,16.0,16.0],"texture":"#0"}}},{"from":[8.4106641,4.106666666666667,7.5893307666666665],"to":[9.231997433333333,4.928000000000001,8.4106641],"faces":{"north":{"uv":[0.0,0.0,16.0,16.0],"texture":"#0"},"east":{"uv":[0.0,0.0,16.0,16.0],"texture":"#0"},"south":{"uv":[0.0,0.0,16.0,16.0],"texture":"#0"},"up":{"uv":[0.0,0.0,16.0,16.0],"texture":"#0"},"down":{"uv":[0.0,0.0,16.0,16.0],"texture":"#0"}}},{"from":[7.5893307666666665,4.106666666666667,8.4106641],"to":[8.4106641,4.928000000000001,9.231997433333333],"faces":{"east":{"uv":[0.0,0.0,16.0,16.0],"texture":"#0"},"south":{"uv":[0.0,0.0,16.0,16.0],"texture":"#0"},"west":{"uv":[0.0,0.0,16.0,16.0],"texture":"#0"},"up":{"uv":[0.0,0.0,16.0,16.0],"texture":"#0"},"down":{"uv":[0.0,0.0,16.0,16.0],"texture":"#0"}}},{"from":[6.767997433333333,3.2853333333333334,6.767997433333333],"to":[7.5893307666666665,4.106666666666667,7.5893307666666665],"faces":{"north":{"uv":[0.0,0.0,16.0,16.0],"texture":"#0"},"east":{"uv":[0.0,0.0,16.0,16.0],"texture":"#0"},"south":{"uv":[0.0,0.0,16.0,16.0],"texture":"#0"},"west":{"uv":[0.0,0.0,16.0,16.0],"texture":"#0"},"up":{"uv":[0.0,0.0,16.0,16.0],"texture":"#0"},"down":{"uv":[0.0,0.0,16.0,16.0],"texture":"#0"}}},{"from":[7.5893307666666665,6.570666666666667,7.5893307666666665],"to":[8.4106641,7.392,8.4106641],"faces":{"north":{"uv":[0.0,0.0,16.0,16.0],"texture":"#0"},"east":{"uv":[0.0,0.0,16.0,16.0],"texture":"#0"},"south":{"uv":[0.0,0.0,16.0,16.0],"texture":"#0"},"west":{"uv":[0.0,0.0,16.0,16.0],"texture":"#0"},"up":{"uv":[0.0,0.0,16.0,16.0],"texture":"#0"}}},{"from":[6.767997433333333,1.6426666666666667,6.767997433333333],"to":[7.5893307666666665,2.464,7.5893307666666665],"faces":{"north":{"uv":[0.0,0.0,16.0,16.0],"texture":"#0"},"east":{"uv":[0.0,0.0,16.0,16.0],"texture":"#0"},"south":{"uv":[0.0,0.0,16.0,16.0],"texture":"#0"},"west":{"uv":[0.0,0.0,16.0,16.0],"texture":"#0"},"up":{"uv":[0.0,0.0,16.0,16.0],"texture":"#0"},"down":{"uv":[0.0,0.0,16.0,16.0],"texture":"#0"}}},{"from":[7.5893307666666665,3.2853333333333334,6.767997433333333],"to":[8.4106641,4.106666666666667,7.5893307666666665],"faces":{"north":{"uv":[0.0,0.0,16.0,16.0],"texture":"#0"},"east":{"uv":[0.0,0.0,16.0,16.0],"texture":"#0"},"west":{"uv":[0.0,0.0,16.0,16.0],"texture":"#0"},"up":{"uv":[0.0,0.0,16.0,16.0],"texture":"#0"},"down":{"uv":[0.0,0.0,16.0,16.0],"texture":"#0"}}},{"from":[6.767997433333333,3.2853333333333334,5.9466641],"to":[7.5893307666666665,4.106666666666667,6.767997433333333],"faces":{"north":{"uv":[0.0,0.0,16.0,16.0],"texture":"#0"},"east":{"uv":[0.0,0.0,16.0,16.0],"texture":"#0"},"south":{"uv":[0.0,0.0,16.0,16.0],"texture":"#0"},"west":{"uv":[0.0,0.0,16.0,16.0],"texture":"#0"},"up":{"uv":[0.0,0.0,16.0,16.0],"texture":"#0"},"down":{"uv":[0.0,0.0,16.0,16.0],"texture":"#0"}}},{"from":[6.767997433333333,3.2853333333333334,7.5893307666666665],"to":[7.5893307666666665,4.106666666666667,8.4106641],"faces":{"north":{"uv":[0.0,0.0,16.0,16.0],"texture":"#0"},"south":{"uv":[0.0,0.0,16.0,16.0],"texture":"#0"},"west":{"uv":[0.0,0.0,16.0,16.0],"texture":"#0"},"up":{"uv":[0.0,0.0,16.0,16.0],"texture":"#0"},"down":{"uv":[0.0,0.0,16.0,16.0],"texture":"#0"}}},{"from":[5.9466641,3.2853333333333334,6.767997433333333],"to":[6.767997433333333,4.106666666666667,7.5893307666666665],"faces":{"north":{"uv":[0.0,0.0,16.0,16.0],"texture":"#0"},"east":{"uv":[0.0,0.0,16.0,16.0],"texture":"#0"},"south":{"uv":[0.0,0.0,16.0,16.0],"texture":"#0"},"west":{"uv":[0.0,0.0,16.0,16.0],"texture":"#0"},"up":{"uv":[0.0,0.0,16.0,16.0],"texture":"#0"},"down":{"uv":[0.0,0.0,16.0,16.0],"texture":"#0"}}},{"from":[8.4106641,3.2853333333333334,6.767997433333333],"to":[9.231997433333333,4.106666666666667,7.5893307666666665],"faces":{"north":{"uv":[0.0,0.0,16.0,16.0],"texture":"#0"},"east":{"uv":[0.0,0.0,16.0,16.0],"texture":"#0"},"south":{"uv":[0.0,0.0,16.0,16.0],"texture":"#0"},"west":{"uv":[0.0,0.0,16.0,16.0],"texture":"#0"},"up":{"uv":[0.0,0.0,16.0,16.0],"texture":"#0"},"down":{"uv":[0.0,0.0,16.0,16.0],"texture":"#0"}}},{"from":[7.5893307666666665,2.464,6.767997433333333],"to":[8.4106641,3.2853333333333334,7.5893307666666665],"faces":{"north":{"uv":[0.0,0.0,16.0,16.0],"texture":"#0"},"east":{"uv":[0.0,0.0,16.0,16.0],"texture":"#0"},"west":{"uv":[0.0,0.0,16.0,16.0],"texture":"#0"},"up":{"uv":[0.0,0.0,16.0,16.0],"texture":"#0"},"down":{"uv":[0.0,0.0,16.0,16.0],"texture":"#0"}}},{"from":[6.767997433333333,2.464,7.5893307666666665],"to":[7.5893307666666665,3.2853333333333334,8.4106641],"faces":{"north":{"uv":[0.0,0.0,16.0,16.0],"texture":"#0"},"south":{"uv":[0.0,0.0,16.0,16.0],"texture":"#0"},"west":{"uv":[0.0,0.0,16.0,16.0],"texture":"#0"},"up":{"uv":[0.0,0.0,16.0,16.0],"texture":"#0"},"down":{"uv":[0.0,0.0,16.0,16.0],"texture":"#0"}}},{"from":[6.767997433333333,3.2853333333333334,8.4106641],"to":[7.5893307666666665,4.106666666666667,9.231997433333333],"faces":{"north":{"uv":[0.0,0.0,16.0,16.0],"texture":"#0"},"east":{"uv":[0.0,0.0,16.0,16.0],"texture":"#0"},"south":{"uv":[0.0,0.0,16.0,16.0],"texture":"#0"},"west":{"uv":[0.0,0.0,16.0,16.0],"texture":"#0"},"up":{"uv":[0.0,0.0,16.0,16.0],"texture":"#0"},"down":{"uv":[0.0,0.0,16.0,16.0],"texture":"#0"}}},{"from":[7.5893307666666665,4.928,7.5893307666666665],"to":[8.4106641,5.7493333333333325,8.4106641],"faces":{"north":{"uv":[0.0,0.0,16.0,16.0],"texture":"#1"},"east":{"uv":[0.0,0.0,16.0,16.0],"texture":"#1"},"south":{"uv":[0.0,0.0,16.0,16.0],"texture":"#1"},"west":{"uv":[0.0,0.0,16.0,16.0],"texture":"#1"}}},{"from":[7.5893307666666665,1.6426666666666667,6.767997433333333],"to":[8.4106641,2.464,7.5893307666666665],"faces":{"north":{"uv":[0.0,0.0,16.0,16.0],"texture":"#0"},"east":{"uv":[0.0,0.0,16.0,16.0],"texture":"#0"},"west":{"uv":[0.0,0.0,16.0,16.0],"texture":"#0"},"up":{"uv":[0.0,0.0,16.0,16.0],"texture":"#0"},"down":{"uv":[0.0,0.0,16.0,16.0],"texture":"#0"}}},{"from":[9.231997433333333,3.2853333333333334,6.767997433333333],"to":[10.053330766666667,4.106666666666667,7.5893307666666665],"faces":{"north":{"uv":[0.0,0.0,16.0,16.0],"texture":"#0"},"east":{"uv":[0.0,0.0,16.0,16.0],"texture":"#0"},"south":{"uv":[0.0,0.0,16.0,16.0],"texture":"#0"},"west":{"uv":[0.0,0.0,16.0,16.0],"texture":"#0"},"up":{"uv":[0.0,0.0,16.0,16.0],"texture":"#0"},"down":{"uv":[0.0,0.0,16.0,16.0],"texture":"#0"}}},{"from":[6.767997433333333,1.6426666666666667,5.9466641],"to":[7.5893307666666665,2.464,6.767997433333333],"faces":{"north":{"uv":[0.0,0.0,16.0,16.0],"texture":"#0"},"east":{"uv":[0.0,0.0,16.0,16.0],"texture":"#0"},"south":{"uv":[0.0,0.0,16.0,16.0],"texture":"#0"},"west":{"uv":[0.0,0.0,16.0,16.0],"texture":"#0"},"up":{"uv":[0.0,0.0,16.0,16.0],"texture":"#0"},"down":{"uv":[0.0,0.0,16.0,16.0],"texture":"#0"}}},{"from":[6.767997433333333,1.6426666666666667,7.5893307666666665],"to":[7.5893307666666665,2.464,8.4106641],"faces":{"north":{"uv":[0.0,0.0,16.0,16.0],"texture":"#0"},"south":{"uv":[0.0,0.0,16.0,16.0],"texture":"#0"},"west":{"uv":[0.0,0.0,16.0,16.0],"texture":"#0"},"up":{"uv":[0.0,0.0,16.0,16.0],"texture":"#0"},"down":{"uv":[0.0,0.0,16.0,16.0],"texture":"#0"}}},{"from":[7.5893307666666665,3.2853333333333334,5.9466641],"to":[8.4106641,4.106666666666667,6.767997433333333],"faces":{"north":{"uv":[0.0,0.0,16.0,16.0],"texture":"#0"},"east":{"uv":[0.0,0.0,16.0,16.0],"texture":"#0"},"south":{"uv":[0.0,0.0,16.0,16.0],"texture":"#0"},"west":{"uv":[0.0,0.0,16.0,16.0],"texture":"#0"},"up":{"uv":[0.0,0.0,16.0,16.0],"texture":"#0"},"down":{"uv":[0.0,0.0,16.0,16.0],"texture":"#0"}}},{"from":[7.5893307666666665,3.2853333333333334,7.5893307666666665],"to":[8.4106641,4.106666666666667,8.4106641],"faces":{"north":{"uv":[0.0,0.0,16.0,16.0],"texture":"#1"},"east":{"uv":[0.0,0.0,16.0,16.0],"texture":"#1"},"south":{"uv":[0.0,0.0,16.0,16.0],"texture":"#1"},"west":{"uv":[0.0,0.0,16.0,16.0],"texture":"#1"}}},{"from":[5.9466641,1.6426666666666667,6.767997433333333],"to":[6.767997433333333,2.464,7.5893307666666665],"faces":{"north":{"uv":[0.0,0.0,16.0,16.0],"texture":"#0"},"east":{"uv":[0.0,0.0,16.0,16.0],"texture":"#0"},"south":{"uv":[0.0,0.0,16.0,16.0],"texture":"#0"},"west":{"uv":[0.0,0.0,16.0,16.0],"texture":"#0"},"up":{"uv":[0.0,0.0,16.0,16.0],"texture":"#0"},"down":{"uv":[0.0,0.0,16.0,16.0],"texture":"#0"}}},{"from":[6.767997433333333,3.2853333333333334,9.231997433333333],"to":[7.5893307666666665,4.106666666666667,10.053330766666667],"faces":{"north":{"uv":[0.0,0.0,16.0,16.0],"texture":"#0"},"east":{"uv":[0.0,0.0,16.0,16.0],"texture":"#0"},"south":{"uv":[0.0,0.0,16.0,16.0],"texture":"#0"},"west":{"uv":[0.0,0.0,16.0,16.0],"texture":"#0"},"up":{"uv":[0.0,0.0,16.0,16.0],"texture":"#0"},"down":{"uv":[0.0,0.0,16.0,16.0],"texture":"#0"}}},{"from":[5.9466641,3.2853333333333334,7.5893307666666665],"to":[6.767997433333333,4.106666666666667,8.4106641],"faces":{"north":{"uv":[0.0,0.0,16.0,16.0],"texture":"#0"},"east":{"uv":[0.0,0.0,16.0,16.0],"texture":"#0"},"south":{"uv":[0.0,0.0,16.0,16.0],"texture":"#0"},"west":{"uv":[0.0,0.0,16.0,16.0],"texture":"#0"},"up":{"uv":[0.0,0.0,16.0,16.0],"texture":"#0"},"down":{"uv":[0.0,0.0,16.0,16.0],"texture":"#0"}}},{"from":[8.4106641,1.6426666666666667,6.767997433333333],"to":[9.231997433333333,2.464,7.5893307666666665],"faces":{"north":{"uv":[0.0,0.0,16.0,16.0],"texture":"#0"},"east":{"uv":[0.0,0.0,16.0,16.0],"texture":"#0"},"south":{"uv":[0.0,0.0,16.0,16.0],"texture":"#0"},"west":{"uv":[0.0,0.0,16.0,16.0],"texture":"#0"},"up":{"uv":[0.0,0.0,16.0,16.0],"texture":"#0"},"down":{"uv":[0.0,0.0,16.0,16.0],"texture":"#0"}}},{"from":[7.5893307666666665,2.464,7.5893307666666665],"to":[8.4106641,3.2853333333333334,8.4106641],"faces":{"north":{"uv":[0.0,0.0,16.0,16.0],"texture":"#1"},"east":{"uv":[0.0,0.0,16.0,16.0],"texture":"#1"},"south":{"uv":[0.0,0.0,16.0,16.0],"texture":"#1"},"west":{"uv":[0.0,0.0,16.0,16.0],"texture":"#1"}}},{"from":[8.4106641,3.2853333333333334,5.9466641],"to":[9.231997433333333,4.106666666666667,6.767997433333333],"faces":{"north":{"uv":[0.0,0.0,16.0,16.0],"texture":"#0"},"east":{"uv":[0.0,0.0,16.0,16.0],"texture":"#0"},"south":{"uv":[0.0,0.0,16.0,16.0],"texture":"#0"},"west":{"uv":[0.0,0.0,16.0,16.0],"texture":"#0"},"up":{"uv":[0.0,0.0,16.0,16.0],"texture":"#0"},"down":{"uv":[0.0,0.0,16.0,16.0],"texture":"#0"}}},{"from":[8.4106641,3.2853333333333334,7.5893307666666665],"to":[9.231997433333333,4.106666666666667,8.4106641],"faces":{"north":{"uv":[0.0,0.0,16.0,16.0],"texture":"#0"},"east":{"uv":[0.0,0.0,16.0,16.0],"texture":"#0"},"south":{"uv":[0.0,0.0,16.0,16.0],"texture":"#0"},"up":{"uv":[0.0,0.0,16.0,16.0],"texture":"#0"},"down":{"uv":[0.0,0.0,16.0,16.0],"texture":"#0"}}},{"from":[6.767997433333333,1.6426666666666667,8.4106641],"to":[7.5893307666666665,2.464,9.231997433333333],"faces":{"north":{"uv":[0.0,0.0,16.0,16.0],"texture":"#0"},"east":{"uv":[0.0,0.0,16.0,16.0],"texture":"#0"},"south":{"uv":[0.0,0.0,16.0,16.0],"texture":"#0"},"west":{"uv":[0.0,0.0,16.0,16.0],"texture":"#0"},"up":{"uv":[0.0,0.0,16.0,16.0],"texture":"#0"},"down":{"uv":[0.0,0.0,16.0,16.0],"texture":"#0"}}},{"from":[7.5893307666666665,3.2853333333333334,8.4106641],"to":[8.4106641,4.106666666666667,9.231997433333333],"faces":{"east":{"uv":[0.0,0.0,16.0,16.0],"texture":"#0"},"south":{"uv":[0.0,0.0,16.0,16.0],"texture":"#0"},"west":{"uv":[0.0,0.0,16.0,16.0],"texture":"#0"},"up":{"uv":[0.0,0.0,16.0,16.0],"texture":"#0"},"down":{"uv":[0.0,0.0,16.0,16.0],"texture":"#0"}}},{"from":[5.9466641,3.2853333333333334,8.4106641],"to":[6.767997433333333,4.106666666666667,9.231997433333333],"faces":{"north":{"uv":[0.0,0.0,16.0,16.0],"texture":"#0"},"east":{"uv":[0.0,0.0,16.0,16.0],"texture":"#0"},"south":{"uv":[0.0,0.0,16.0,16.0],"texture":"#0"},"west":{"uv":[0.0,0.0,16.0,16.0],"texture":"#0"},"up":{"uv":[0.0,0.0,16.0,16.0],"texture":"#0"},"down":{"uv":[0.0,0.0,16.0,16.0],"texture":"#0"}}}]}