{"parent":"nova:block_base","textures":{"1":"block/crimson_stem","0":"block/nether_wart_block","4":"block/weeping_vines_plant","5":"block/shroomlight","3":"block/weeping_vines","2":"block/crimson_stem_top"},"elements":[{"from":[8.399999999999999,2.4000000000000004,6.0],"to":[9.2,3.2,6.8],"faces":{"north":{"uv":[0.0,0.0,16.0,16.0],"texture":"#0"},"east":{"uv":[0.0,0.0,16.0,16.0],"texture":"#0"},"south":{"uv":[0.0,0.0,16.0,16.0],"texture":"#0"},"west":{"uv":[0.0,0.0,16.0,16.0],"texture":"#0"}}},{"from":[9.2,1.6,6.8],"to":[10.0,2.4000000000000004,7.6000000000000005],"faces":{"north":{"uv":[0.0,0.0,16.0,16.0],"texture":"#0"},"east":{"uv":[0.0,0.0,16.0,16.0],"texture":"#0"},"south":{"uv":[0.0,0.0,16.0,16.0],"texture":"#0"},"west":{"uv":[0.0,0.0,16.0,16.0],"texture":"#0"},"down":{"uv":[0.0,0.0,16.0,16.0],"texture":"#0"}}},{"from":[7.6000000000000005,1.6,7.6000000000000005],"to":[8.399999999999999,2.4000000000000004,8.399999999999999],"faces":{"north":{"uv":[0.0,0.0,16.0,16.0],"texture":"#1"},"east":{"uv":[0.0,0.0,16.0,16.0],"texture":"#1"},"south":{"uv":[0.0,0.0,16.0,16.0],"texture":"#1"},"west":{"uv":[0.0,0.0,16.0,16.0],"texture":"#1"}}},{"from":[7.6000000000000005,0.0,7.6000000000000005],"to":[8.399999999999999,0.8,8.399999999999999],"faces":{"north":{"uv":[0.0,0.0,16.0,16.0],"texture":"#1"},"east":{"uv":[0.0,0.0,16.0,16.0],"texture":"#1"},"south":{"uv":[0.0,0.0,16.0,16.0],"texture":"#1"},"west":{"uv":[0.0,0.0,16.0,16.0],"texture":"#1"},"down":{"uv":[0.0,0.0,16.0,16.0],"texture":"#2"}}},{"from":[9.2,3.2,7.6000000000000005],"to":[10.0,4.0,8.399999999999999],"faces":{"east":{"uv":[0.0,0.0,16.0,16.0],"texture":"#0"},"south":{"uv":[0.0,0.0,16.0,16.0],"texture":"#0"},"west":{"uv":[0.0,0.0,16.0,16.0],"texture":"#0"}}},{"from":[9.2,4.0,8.399999999999999],"to":[10.0,4.800000000000001,9.2],"faces":{"east":{"uv":[0.0,0.0,16.0,16.0],"texture":"#0"},"south":{"uv":[0.0,0.0,16.0,16.0],"texture":"#0"},"west":{"uv":[0.0,0.0,16.0,16.0],"texture":"#0"},"up":{"uv":[0.0,0.0,16.0,16.0],"texture":"#0"},"down":{"uv":[0.0,0.0,16.0,16.0],"texture":"#0"}}},{"from":[8.399999999999999,4.0,9.2],"to":[9.2,4.800000000000001,10.0],"faces":{"north":{"uv":[0.0,0.0,16.0,16.0],"texture":"#0"},"east":{"uv":[0.0,0.0,16.0,16.0],"texture":"#0"},"south":{"uv":[0.0,0.0,16.0,16.0],"texture":"#0"},"up":{"uv":[0.0,0.0,16.0,16.0],"texture":"#0"},"down":{"uv":[0.0,0.0,16.0,16.0],"texture":"#0"}}},{"from":[8.399999999999999,1.6,6.0],"to":[9.2,2.4000000000000004,6.8],"faces":{"north":{"uv":[0.0,0.0,16.0,16.0],"texture":"#0"},"east":{"uv":[0.0,0.0,16.0,16.0],"texture":"#0"},"south":{"uv":[0.0,0.0,16.0,16.0],"texture":"#0"},"west":{"uv":[0.0,0.0,16.0,16.0],"texture":"#0"},"down":{"uv":[0.0,0.0,16.0,16.0],"texture":"#0"}}},{"from":[9.2,2.4000000000000004,7.6000000000000005],"to":[10.0,3.2,8.399999999999999],"faces":{"east":{"uv":[0.0,0.0,16.0,16.0],"texture":"#0"},"south":{"uv":[0.0,0.0,16.0,16.0],"texture":"#0"},"west":{"uv":[0.0,0.0,16.0,16.0],"texture":"#0"},"down":{"uv":[0.0,0.0,16.0,16.0],"texture":"#0"}}},{"from":[8.440000000000001,0.0,6.3999999999999995],"to":[9.16,0.8,6.3999999999999995],"shade":false,"rotation":{"angle":45.0,"axis":"y","origin":[8.8,0.4,6.3999999999999995],"rescale":true},"faces":{"north":{"uv":[0.0,0.0,16.0,16.0],"texture":"#3"},"south":{"uv":[0.0,0.0,16.0,16.0],"texture":"#3"}}},{"from":[8.8,0.0,6.04],"to":[8.8,0.8,6.76],"shade":false,"rotation":{"angle":45.0,"axis":"y","origin":[8.8,0.4,6.3999999999999995],"rescale":true},"faces":{"east":{"uv":[0.0,0.0,16.0,16.0],"texture":"#3"},"west":{"uv":[0.0,0.0,16.0,16.0],"texture":"#3"}}},{"from":[7.6000000000000005,0.8,7.6000000000000005],"to":[8.399999999999999,1.6,8.399999999999999],"faces":{"north":{"uv":[0.0,0.0,16.0,16.0],"texture":"#1"},"east":{"uv":[0.0,0.0,16.0,16.0],"texture":"#1"},"south":{"uv":[0.0,0.0,16.0,16.0],"texture":"#1"},"west":{"uv":[0.0,0.0,16.0,16.0],"texture":"#1"}}},{"from":[9.2,3.2,9.2],"to":[10.0,4.0,10.0],"faces":{"north":{"uv":[0.0,0.0,16.0,16.0],"texture":"#0"},"east":{"uv":[0.0,0.0,16.0,16.0],"texture":"#0"},"south":{"uv":[0.0,0.0,16.0,16.0],"texture":"#0"},"west":{"uv":[0.0,0.0,16.0,16.0],"texture":"#0"},"up":{"uv":[0.0,0.0,16.0,16.0],"texture":"#0"}}},{"from":[9.2,2.4000000000000004,9.2],"to":[10.0,3.2,10.0],"faces":{"north":{"uv":[0.0,0.0,16.0,16.0],"texture":"#0"},"east":{"uv":[0.0,0.0,16.0,16.0],"texture":"#0"},"south":{"uv":[0.0,0.0,16.0,16.0],"texture":"#0"},"west":{"uv":[0.0,0.0,16.0,16.0],"texture":"#0"},"down":{"uv":[0.0,0.0,16.0,16.0],"texture":"#0"}}},{"from":[8.440000000000001,0.8,6.3999999999999995],"to":[9.16,1.6,6.3999999999999995],"shade":false,"rotation":{"angle":45.0,"axis":"y","origin":[8.8,1.2000000000000002,6.3999999999999995],"rescale":true},"faces":{"north":{"uv":[0.0,0.0,16.0,16.0],"texture":"#4"},"south":{"uv":[0.0,0.0,16.0,16.0],"texture":"#4"}}},{"from":[8.8,0.8,6.04],"to":[8.8,1.6,6.76],"shade":false,"rotation":{"angle":45.0,"axis":"y","origin":[8.8,1.2000000000000002,6.3999999999999995],"rescale":true},"faces":{"east":{"uv":[0.0,0.0,16.0,16.0],"texture":"#4"},"west":{"uv":[0.0,0.0,16.0,16.0],"texture":"#4"}}},{"from":[9.239999999999998,1.6,9.600000000000001],"to":[9.96,2.4000000000000004,9.600000000000001],"shade":false,"rotation":{"angle":45.0,"axis":"y","origin":[9.600000000000001,2.0,9.600000000000001],"rescale":true},"faces":{"north":{"uv":[0.0,0.0,16.0,16.0],"texture":"#4"},"south":{"uv":[0.0,0.0,16.0,16.0],"texture":"#4"}}},{"from":[9.600000000000001,1.6,9.239999999999998],"to":[9.600000000000001,2.4000000000000004,9.96],"shade":false,"rotation":{"angle":45.0,"axis":"y","origin":[9.600000000000001,2.0,9.600000000000001],"rescale":true},"faces":{"east":{"uv":[0.0,0.0,16.0,16.0],"texture":"#4"},"west":{"uv":[0.0,0.0,16.0,16.0],"texture":"#4"}}},{"from":[9.239999999999998,0.0,9.600000000000001],"to":[9.96,0.8,9.600000000000001],"shade":false,"rotation":{"angle":45.0,"axis":"y","origin":[9.600000000000001,0.4,9.600000000000001],"rescale":true},"faces":{"north":{"uv":[0.0,0.0,16.0,16.0],"texture":"#3"},"south":{"uv":[0.0,0.0,16.0,16.0],"texture":"#3"}}},{"from":[9.600000000000001,0.0,9.239999999999998],"to":[9.600000000000001,0.8,9.96],"shade":false,"rotation":{"angle":45.0,"axis":"y","origin":[9.600000000000001,0.4,9.600000000000001],"rescale":true},"faces":{"east":{"uv":[0.0,0.0,16.0,16.0],"texture":"#3"},"west":{"uv":[0.0,0.0,16.0,16.0],"texture":"#3"}}},{"from":[9.239999999999998,0.8,9.600000000000001],"to":[9.96,1.6,9.600000000000001],"shade":false,"rotation":{"angle":45.0,"axis":"y","origin":[9.600000000000001,1.2000000000000002,9.600000000000001],"rescale":true},"faces":{"north":{"uv":[0.0,0.0,16.0,16.0],"texture":"#4"},"south":{"uv":[0.0,0.0,16.0,16.0],"texture":"#4"}}},{"from":[9.600000000000001,0.8,9.239999999999998],"to":[9.600000000000001,1.6,9.96],"shade":false,"rotation":{"angle":45.0,"axis":"y","origin":[9.600000000000001,1.2000000000000002,9.600000000000001],"rescale":true},"faces":{"east":{"uv":[0.0,0.0,16.0,16.0],"texture":"#4"},"west":{"uv":[0.0,0.0,16.0,16.0],"texture":"#4"}}},{"from":[6.8,5.6000000000000005,6.8],"to":[7.6000000000000005,6.4,7.6000000000000005],"faces":{"north":{"uv":[0.0,0.0,16.0,16.0],"texture":"#0"},"west":{"uv":[0.0,0.0,16.0,16.0],"texture":"#0"},"up":{"uv":[0.0,0.0,16.0,16.0],"texture":"#0"}}},{"from":[6.8,4.800000000000001,6.8],"to":[7.6000000000000005,5.6000000000000005,7.6000000000000005],"faces":{"north":{"uv":[0.0,0.0,16.0,16.0],"texture":"#0"},"west":{"uv":[0.0,0.0,16.0,16.0],"texture":"#0"}}},{"from":[6.8,4.0,6.8],"to":[7.6000000000000005,4.800000000000001,7.6000000000000005],"faces":{"east":{"uv":[0.0,0.0,16.0,16.0],"texture":"#5"},"south":{"uv":[0.0,0.0,16.0,16.0],"texture":"#5"},"down":{"uv":[0.0,0.0,16.0,16.0],"texture":"#5"}}},{"from":[6.8,5.6000000000000005,7.6000000000000005],"to":[7.6000000000000005,6.4,8.399999999999999],"faces":{"west":{"uv":[0.0,0.0,16.0,16.0],"texture":"#0"},"up":{"uv":[0.0,0.0,16.0,16.0],"texture":"#0"}}},{"from":[7.6000000000000005,5.6000000000000005,6.8],"to":[8.399999999999999,6.4,7.6000000000000005],"faces":{"north":{"uv":[0.0,0.0,16.0,16.0],"texture":"#0"},"up":{"uv":[0.0,0.0,16.0,16.0],"texture":"#0"}}},{"from":[7.6000000000000005,4.800000000000001,6.8],"to":[8.399999999999999,5.6000000000000005,7.6000000000000005],"faces":{"north":{"uv":[0.0,0.0,16.0,16.0],"texture":"#0"},"down":{"uv":[0.0,0.0,16.0,16.0],"texture":"#0"}}},{"from":[6.8,4.800000000000001,7.6000000000000005],"to":[7.6000000000000005,5.6000000000000005,8.399999999999999],"faces":{"west":{"uv":[0.0,0.0,16.0,16.0],"texture":"#0"},"down":{"uv":[0.0,0.0,16.0,16.0],"texture":"#0"}}},{"from":[6.8,5.6000000000000005,8.399999999999999],"to":[7.6000000000000005,6.4,9.2],"faces":{"south":{"uv":[0.0,0.0,16.0,16.0],"texture":"#0"},"west":{"uv":[0.0,0.0,16.0,16.0],"texture":"#0"},"up":{"uv":[0.0,0.0,16.0,16.0],"texture":"#0"}}},{"from":[6.8,4.0,6.0],"to":[7.6000000000000005,4.800000000000001,6.8],"faces":{"north":{"uv":[0.0,0.0,16.0,16.0],"texture":"#0"},"up":{"uv":[0.0,0.0,16.0,16.0],"texture":"#0"}}},{"from":[8.399999999999999,5.6000000000000005,6.8],"to":[9.2,6.4,7.6000000000000005],"faces":{"north":{"uv":[0.0,0.0,16.0,16.0],"texture":"#0"},"east":{"uv":[0.0,0.0,16.0,16.0],"texture":"#0"},"up":{"uv":[0.0,0.0,16.0,16.0],"texture":"#0"}}},{"from":[6.0,4.0,6.8],"to":[6.8,4.800000000000001,7.6000000000000005],"faces":{"west":{"uv":[0.0,0.0,16.0,16.0],"texture":"#0"},"up":{"uv":[0.0,0.0,16.0,16.0],"texture":"#0"}}},{"from":[6.8,3.2,6.0],"to":[7.6000000000000005,4.0,6.8],"faces":{"north":{"uv":[0.0,0.0,16.0,16.0],"texture":"#0"},"south":{"uv":[0.0,0.0,16.0,16.0],"texture":"#0"},"west":{"uv":[0.0,0.0,16.0,16.0],"texture":"#0"}}},{"from":[6.0,3.2,6.8],"to":[6.8,4.0,7.6000000000000005],"faces":{"north":{"uv":[0.0,0.0,16.0,16.0],"texture":"#0"},"east":{"uv":[0.0,0.0,16.0,16.0],"texture":"#0"},"west":{"uv":[0.0,0.0,16.0,16.0],"texture":"#0"}}},{"from":[8.399999999999999,4.800000000000001,6.8],"to":[9.2,5.6000000000000005,7.6000000000000005],"faces":{"north":{"uv":[0.0,0.0,16.0,16.0],"texture":"#0"},"east":{"uv":[0.0,0.0,16.0,16.0],"texture":"#0"}}},{"from":[6.8,4.800000000000001,8.399999999999999],"to":[7.6000000000000005,5.6000000000000005,9.2],"faces":{"south":{"uv":[0.0,0.0,16.0,16.0],"texture":"#0"},"west":{"uv":[0.0,0.0,16.0,16.0],"texture":"#0"}}},{"from":[6.8,4.0,8.399999999999999],"to":[7.6000000000000005,4.800000000000001,9.2],"faces":{"north":{"uv":[0.0,0.0,16.0,16.0],"texture":"#5"},"down":{"uv":[0.0,0.0,16.0,16.0],"texture":"#5"}}},{"from":[8.399999999999999,4.0,6.8],"to":[9.2,4.800000000000001,7.6000000000000005],"faces":{"south":{"uv":[0.0,0.0,16.0,16.0],"texture":"#5"},"west":{"uv":[0.0,0.0,16.0,16.0],"texture":"#5"},"down":{"uv":[0.0,0.0,16.0,16.0],"texture":"#5"}}},{"from":[7.6000000000000005,5.6000000000000005,7.6000000000000005],"to":[8.399999999999999,6.4,8.399999999999999],"faces":{"up":{"uv":[0.0,0.0,16.0,16.0],"texture":"#0"}}},{"from":[6.8,2.4000000000000004,6.0],"to":[7.6000000000000005,3.2,6.8],"faces":{"north":{"uv":[0.0,0.0,16.0,16.0],"texture":"#0"},"east":{"uv":[0.0,0.0,16.0,16.0],"texture":"#0"},"south":{"uv":[0.0,0.0,16.0,16.0],"texture":"#0"},"west":{"uv":[0.0,0.0,16.0,16.0],"texture":"#0"},"down":{"uv":[0.0,0.0,16.0,16.0],"texture":"#0"}}},{"from":[6.0,2.4000000000000004,6.8],"to":[6.8,3.2,7.6000000000000005],"faces":{"north":{"uv":[0.0,0.0,16.0,16.0],"texture":"#0"},"east":{"uv":[0.0,0.0,16.0,16.0],"texture":"#0"},"south":{"uv":[0.0,0.0,16.0,16.0],"texture":"#0"},"west":{"uv":[0.0,0.0,16.0,16.0],"texture":"#0"},"down":{"uv":[0.0,0.0,16.0,16.0],"texture":"#0"}}},{"from":[6.0,4.0,6.0],"to":[6.8,4.800000000000001,6.8],"faces":{"north":{"uv":[0.0,0.0,16.0,16.0],"texture":"#0"},"west":{"uv":[0.0,0.0,16.0,16.0],"texture":"#0"},"up":{"uv":[0.0,0.0,16.0,16.0],"texture":"#0"},"down":{"uv":[0.0,0.0,16.0,16.0],"texture":"#0"}}},{"from":[7.6000000000000005,4.0,6.0],"to":[8.399999999999999,4.800000000000001,6.8],"faces":{"north":{"uv":[0.0,0.0,16.0,16.0],"texture":"#0"},"south":{"uv":[0.0,0.0,16.0,16.0],"texture":"#0"},"up":{"uv":[0.0,0.0,16.0,16.0],"texture":"#0"}}},{"from":[7.6000000000000005,4.0,7.6000000000000005],"to":[8.399999999999999,4.800000000000001,8.399999999999999],"faces":{"north":{"uv":[0.0,0.0,16.0,16.0],"texture":"#1"},"east":{"uv":[0.0,0.0,16.0,16.0],"texture":"#1"},"west":{"uv":[0.0,0.0,16.0,16.0],"texture":"#1"}}},{"from":[9.2,4.0,6.8],"to":[10.0,4.800000000000001,7.6000000000000005],"faces":{"east":{"uv":[0.0,0.0,16.0,16.0],"texture":"#0"},"up":{"uv":[0.0,0.0,16.0,16.0],"texture":"#0"}}},{"from":[6.8,4.0,9.2],"to":[7.6000000000000005,4.800000000000001,10.0],"faces":{"south":{"uv":[0.0,0.0,16.0,16.0],"texture":"#0"},"up":{"uv":[0.0,0.0,16.0,16.0],"texture":"#0"}}},{"from":[8.399999999999999,5.6000000000000005,7.6000000000000005],"to":[9.2,6.4,8.399999999999999],"faces":{"east":{"uv":[0.0,0.0,16.0,16.0],"texture":"#0"},"up":{"uv":[0.0,0.0,16.0,16.0],"texture":"#0"}}},{"from":[6.0,4.0,7.6000000000000005],"to":[6.8,4.800000000000001,8.399999999999999],"faces":{"east":{"uv":[0.0,0.0,16.0,16.0],"texture":"#0"},"west":{"uv":[0.0,0.0,16.0,16.0],"texture":"#0"},"up":{"uv":[0.0,0.0,16.0,16.0],"texture":"#0"}}},{"from":[7.6000000000000005,5.6000000000000005,8.399999999999999],"to":[8.399999999999999,6.4,9.2],"faces":{"south":{"uv":[0.0,0.0,16.0,16.0],"texture":"#0"},"up":{"uv":[0.0,0.0,16.0,16.0],"texture":"#0"}}},{"from":[7.6000000000000005,3.2,6.0],"to":[8.399999999999999,4.0,6.8],"faces":{"north":{"uv":[0.0,0.0,16.0,16.0],"texture":"#0"},"south":{"uv":[0.0,0.0,16.0,16.0],"texture":"#0"},"down":{"uv":[0.0,0.0,16.0,16.0],"texture":"#0"}}},{"from":[7.6000000000000005,3.2,7.6000000000000005],"to":[8.399999999999999,4.0,8.399999999999999],"faces":{"north":{"uv":[0.0,0.0,16.0,16.0],"texture":"#1"},"east":{"uv":[0.0,0.0,16.0,16.0],"texture":"#1"},"south":{"uv":[0.0,0.0,16.0,16.0],"texture":"#1"},"west":{"uv":[0.0,0.0,16.0,16.0],"texture":"#1"}}},{"from":[9.2,3.2,6.8],"to":[10.0,4.0,7.6000000000000005],"faces":{"north":{"uv":[0.0,0.0,16.0,16.0],"texture":"#0"},"east":{"uv":[0.0,0.0,16.0,16.0],"texture":"#0"},"west":{"uv":[0.0,0.0,16.0,16.0],"texture":"#0"}}},{"from":[6.8,3.2,9.2],"to":[7.6000000000000005,4.0,10.0],"faces":{"north":{"uv":[0.0,0.0,16.0,16.0],"texture":"#0"},"east":{"uv":[0.0,0.0,16.0,16.0],"texture":"#0"},"south":{"uv":[0.0,0.0,16.0,16.0],"texture":"#0"},"west":{"uv":[0.0,0.0,16.0,16.0],"texture":"#0"}}},{"from":[7.6000000000000005,4.800000000000001,8.399999999999999],"to":[8.399999999999999,5.6000000000000005,9.2],"faces":{"south":{"uv":[0.0,0.0,16.0,16.0],"texture":"#0"}}},{"from":[6.0,3.2,7.6000000000000005],"to":[6.8,4.0,8.399999999999999],"faces":{"east":{"uv":[0.0,0.0,16.0,16.0],"texture":"#0"},"west":{"uv":[0.0,0.0,16.0,16.0],"texture":"#0"},"down":{"uv":[0.0,0.0,16.0,16.0],"texture":"#0"}}},{"from":[8.399999999999999,4.800000000000001,7.6000000000000005],"to":[9.2,5.6000000000000005,8.399999999999999],"faces":{"east":{"uv":[0.0,0.0,16.0,16.0],"texture":"#0"},"down":{"uv":[0.0,0.0,16.0,16.0],"texture":"#0"}}},{"from":[7.6000000000000005,4.0,8.399999999999999],"to":[8.399999999999999,4.800000000000001,9.2],"faces":{"east":{"uv":[0.0,0.0,16.0,16.0],"texture":"#5"},"down":{"uv":[0.0,0.0,16.0,16.0],"texture":"#5"}}},{"from":[8.399999999999999,4.0,6.0],"to":[9.2,4.800000000000001,6.8],"faces":{"north":{"uv":[0.0,0.0,16.0,16.0],"texture":"#0"},"up":{"uv":[0.0,0.0,16.0,16.0],"texture":"#0"}}},{"from":[8.399999999999999,5.6000000000000005,8.399999999999999],"to":[9.2,6.4,9.2],"faces":{"east":{"uv":[0.0,0.0,16.0,16.0],"texture":"#0"},"south":{"uv":[0.0,0.0,16.0,16.0],"texture":"#0"},"up":{"uv":[0.0,0.0,16.0,16.0],"texture":"#0"}}},{"from":[6.0,4.0,8.399999999999999],"to":[6.8,4.800000000000001,9.2],"faces":{"west":{"uv":[0.0,0.0,16.0,16.0],"texture":"#0"},"up":{"uv":[0.0,0.0,16.0,16.0],"texture":"#0"}}},{"from":[6.8,2.4000000000000004,9.2],"to":[7.6000000000000005,3.2,10.0],"faces":{"north":{"uv":[0.0,0.0,16.0,16.0],"texture":"#0"},"east":{"uv":[0.0,0.0,16.0,16.0],"texture":"#0"},"south":{"uv":[0.0,0.0,16.0,16.0],"texture":"#0"},"west":{"uv":[0.0,0.0,16.0,16.0],"texture":"#0"},"down":{"uv":[0.0,0.0,16.0,16.0],"texture":"#0"}}},{"from":[9.2,2.4000000000000004,6.8],"to":[10.0,3.2,7.6000000000000005],"faces":{"north":{"uv":[0.0,0.0,16.0,16.0],"texture":"#0"},"east":{"uv":[0.0,0.0,16.0,16.0],"texture":"#0"},"west":{"uv":[0.0,0.0,16.0,16.0],"texture":"#0"}}},{"from":[7.6000000000000005,2.4000000000000004,7.6000000000000005],"to":[8.399999999999999,3.2,8.399999999999999],"faces":{"north":{"uv":[0.0,0.0,16.0,16.0],"texture":"#1"},"east":{"uv":[0.0,0.0,16.0,16.0],"texture":"#1"},"south":{"uv":[0.0,0.0,16.0,16.0],"texture":"#1"},"west":{"uv":[0.0,0.0,16.0,16.0],"texture":"#1"}}},{"from":[8.399999999999999,3.2,6.0],"to":[9.2,4.0,6.8],"faces":{"north":{"uv":[0.0,0.0,16.0,16.0],"texture":"#0"},"east":{"uv":[0.0,0.0,16.0,16.0],"texture":"#0"},"south":{"uv":[0.0,0.0,16.0,16.0],"texture":"#0"}}},{"from":[8.399999999999999,4.800000000000001,8.399999999999999],"to":[9.2,5.6000000000000005,9.2],"faces":{"east":{"uv":[0.0,0.0,16.0,16.0],"texture":"#0"},"south":{"uv":[0.0,0.0,16.0,16.0],"texture":"#0"},"down":{"uv":[0.0,0.0,16.0,16.0],"texture":"#0"}}},{"from":[6.0,3.2,8.399999999999999],"to":[6.8,4.0,9.2],"faces":{"east":{"uv":[0.0,0.0,16.0,16.0],"texture":"#0"},"south":{"uv":[0.0,0.0,16.0,16.0],"texture":"#0"},"west":{"uv":[0.0,0.0,16.0,16.0],"texture":"#0"},"down":{"uv":[0.0,0.0,16.0,16.0],"texture":"#0"}}},{"from":[9.2,4.0,6.0],"to":[10.0,4.800000000000001,6.8],"faces":{"north":{"uv":[0.0,0.0,16.0,16.0],"texture":"#0"},"east":{"uv":[0.0,0.0,16.0,16.0],"texture":"#0"},"up":{"uv":[0.0,0.0,16.0,16.0],"texture":"#0"},"down":{"uv":[0.0,0.0,16.0,16.0],"texture":"#0"}}},{"from":[7.6000000000000005,4.0,9.2],"to":[8.399999999999999,4.800000000000001,10.0],"faces":{"south":{"uv":[0.0,0.0,16.0,16.0],"texture":"#0"},"up":{"uv":[0.0,0.0,16.0,16.0],"texture":"#0"},"down":{"uv":[0.0,0.0,16.0,16.0],"texture":"#0"}}},{"from":[9.2,4.0,7.6000000000000005],"to":[10.0,4.800000000000001,8.399999999999999],"faces":{"east":{"uv":[0.0,0.0,16.0,16.0],"texture":"#0"},"west":{"uv":[0.0,0.0,16.0,16.0],"texture":"#0"},"up":{"uv":[0.0,0.0,16.0,16.0],"texture":"#0"}}},{"from":[6.0,4.0,9.2],"to":[6.8,4.800000000000001,10.0],"faces":{"south":{"uv":[0.0,0.0,16.0,16.0],"texture":"#0"},"west":{"uv":[0.0,0.0,16.0,16.0],"texture":"#0"},"up":{"uv":[0.0,0.0,16.0,16.0],"texture":"#0"},"down":{"uv":[0.0,0.0,16.0,16.0],"texture":"#0"}}}]}