{"parent":"nova:block_base","textures":{"0":"block/brown_mushroom_block","2":"block/mushroom_stem","1":"block/mushroom_block_inside"},"elements":[{"from":[5.232,3.163,8.395],"to":[6.023,3.954,9.186],"faces":{"west":{"uv":[0.0,0.0,16.0,16.0],"texture":"#0"},"up":{"uv":[0.0,0.0,16.0,16.0],"texture":"#0"},"down":{"uv":[0.0,0.0,16.0,16.0],"texture":"#1"}}},{"from":[8.395,3.163,6.814],"to":[9.186,3.954,7.605],"faces":{"up":{"uv":[0.0,0.0,16.0,16.0],"texture":"#0"},"down":{"uv":[0.0,0.0,16.0,16.0],"texture":"#1"}}},{"from":[8.395,3.163,5.232],"to":[9.186,3.954,6.023],"faces":{"north":{"uv":[0.0,0.0,16.0,16.0],"texture":"#0"},"up":{"uv":[0.0,0.0,16.0,16.0],"texture":"#0"},"down":{"uv":[0.0,0.0,16.0,16.0],"texture":"#1"}}},{"from":[7.605,3.163,7.605],"to":[8.395,3.954,8.395],"faces":{"up":{"uv":[0.0,0.0,16.0,16.0],"texture":"#0"}}},{"from":[6.814,3.163,8.395],"to":[7.605,3.954,9.186],"faces":{"up":{"uv":[0.0,0.0,16.0,16.0],"texture":"#0"},"down":{"uv":[0.0,0.0,16.0,16.0],"texture":"#1"}}},{"from":[5.232,3.163,9.186],"to":[6.023,3.954,9.977],"faces":{"south":{"uv":[0.0,0.0,16.0,16.0],"texture":"#0"},"west":{"uv":[0.0,0.0,16.0,16.0],"texture":"#0"},"up":{"uv":[0.0,0.0,16.0,16.0],"texture":"#0"},"down":{"uv":[0.0,0.0,16.0,16.0],"texture":"#1"}}},{"from":[9.186,3.163,5.232],"to":[9.977,3.954,6.023],"faces":{"north":{"uv":[0.0,0.0,16.0,16.0],"texture":"#0"},"east":{"uv":[0.0,0.0,16.0,16.0],"texture":"#0"},"up":{"uv":[0.0,0.0,16.0,16.0],"texture":"#0"},"down":{"uv":[0.0,0.0,16.0,16.0],"texture":"#1"}}},{"from":[9.186,3.163,6.814],"to":[9.977,3.954,7.605],"faces":{"up":{"uv":[0.0,0.0,16.0,16.0],"texture":"#0"},"down":{"uv":[0.0,0.0,16.0,16.0],"texture":"#1"}}},{"from":[6.814,3.163,9.186],"to":[7.605,3.954,9.977],"faces":{"up":{"uv":[0.0,0.0,16.0,16.0],"texture":"#0"},"down":{"uv":[0.0,0.0,16.0,16.0],"texture":"#1"}}},{"from":[7.605,2.373,7.605],"to":[8.395,3.163,8.395],"faces":{"north":{"uv":[0.0,0.0,16.0,16.0],"texture":"#2"},"east":{"uv":[0.0,0.0,16.0,16.0],"texture":"#2"},"south":{"uv":[0.0,0.0,16.0,16.0],"texture":"#2"},"west":{"uv":[0.0,0.0,16.0,16.0],"texture":"#2"}}},{"from":[9.977,3.163,6.814],"to":[10.768,3.954,7.605],"faces":{"east":{"uv":[0.0,0.0,16.0,16.0],"texture":"#0"},"up":{"uv":[0.0,0.0,16.0,16.0],"texture":"#0"},"down":{"uv":[0.0,0.0,16.0,16.0],"texture":"#1"}}},{"from":[8.395,3.163,7.605],"to":[9.186,3.954,8.395],"faces":{"up":{"uv":[0.0,0.0,16.0,16.0],"texture":"#0"},"down":{"uv":[0.0,0.0,16.0,16.0],"texture":"#1"}}},{"from":[7.605,3.163,8.395],"to":[8.395,3.954,9.186],"faces":{"up":{"uv":[0.0,0.0,16.0,16.0],"texture":"#0"},"down":{"uv":[0.0,0.0,16.0,16.0],"texture":"#1"}}},{"from":[6.814,3.163,9.977],"to":[7.605,3.954,10.768],"faces":{"south":{"uv":[0.0,0.0,16.0,16.0],"texture":"#0"},"up":{"uv":[0.0,0.0,16.0,16.0],"texture":"#0"},"down":{"uv":[0.0,0.0,16.0,16.0],"texture":"#1"}}},{"from":[7.605,3.163,9.186],"to":[8.395,3.954,9.977],"faces":{"up":{"uv":[0.0,0.0,16.0,16.0],"texture":"#0"},"down":{"uv":[0.0,0.0,16.0,16.0],"texture":"#1"}}},{"from":[9.186,3.163,7.605],"to":[9.977,3.954,8.395],"faces":{"up":{"uv":[0.0,0.0,16.0,16.0],"texture":"#0"},"down":{"uv":[0.0,0.0,16.0,16.0],"texture":"#1"}}},{"from":[7.605,3.163,9.977],"to":[8.395,3.954,10.768],"faces":{"south":{"uv":[0.0,0.0,16.0,16.0],"texture":"#0"},"up":{"uv":[0.0,0.0,16.0,16.0],"texture":"#0"},"down":{"uv":[0.0,0.0,16.0,16.0],"texture":"#1"}}},{"from":[7.605,1.582,7.605],"to":[8.395,2.373,8.395],"faces":{"north":{"uv":[0.0,0.0,16.0,16.0],"texture":"#2"},"east":{"uv":[0.0,0.0,16.0,16.0],"texture":"#2"},"south":{"uv":[0.0,0.0,16.0,16.0],"texture":"#2"},"west":{"uv":[0.0,0.0,16.0,16.0],"texture":"#2"}}},{"from":[9.977,3.163,7.605],"to":[10.768,3.954,8.395],"faces":{"east":{"uv":[0.0,0.0,16.0,16.0],"texture":"#0"},"up":{"uv":[0.0,0.0,16.0,16.0],"texture":"#0"},"down":{"uv":[0.0,0.0,16.0,16.0],"texture":"#1"}}},{"from":[7.605,0.0,7.605],"to":[8.395,0.791,8.395],"faces":{"north":{"uv":[0.0,0.0,16.0,16.0],"texture":"#2"},"east":{"uv":[0.0,0.0,16.0,16.0],"texture":"#2"},"south":{"uv":[0.0,0.0,16.0,16.0],"texture":"#2"},"west":{"uv":[0.0,0.0,16.0,16.0],"texture":"#2"},"down":{"uv":[0.0,0.0,16.0,16.0],"texture":"#1"}}},{"from":[8.395,3.163,8.395],"to":[9.186,3.954,9.186],"faces":{"up":{"uv":[0.0,0.0,16.0,16.0],"texture":"#0"},"down":{"uv":[0.0,0.0,16.0,16.0],"texture":"#1"}}},{"from":[8.395,3.163,9.186],"to":[9.186,3.954,9.977],"faces":{"up":{"uv":[0.0,0.0,16.0,16.0],"texture":"#0"},"down":{"uv":[0.0,0.0,16.0,16.0],"texture":"#1"}}},{"from":[9.186,3.163,8.395],"to":[9.977,3.954,9.186],"faces":{"up":{"uv":[0.0,0.0,16.0,16.0],"texture":"#0"},"down":{"uv":[0.0,0.0,16.0,16.0],"texture":"#1"}}},{"from":[9.186,3.163,9.186],"to":[9.977,3.954,9.977],"faces":{"up":{"uv":[0.0,0.0,16.0,16.0],"texture":"#0"},"down":{"uv":[0.0,0.0,16.0,16.0],"texture":"#1"}}},{"from":[9.977,3.163,8.395],"to":[10.768,3.954,9.186],"faces":{"east":{"uv":[0.0,0.0,16.0,16.0],"texture":"#0"},"up":{"uv":[0.0,0.0,16.0,16.0],"texture":"#0"},"down":{"uv":[0.0,0.0,16.0,16.0],"texture":"#1"}}},{"from":[8.395,3.163,9.977],"to":[9.186,3.954,10.768],"faces":{"south":{"uv":[0.0,0.0,16.0,16.0],"texture":"#0"},"up":{"uv":[0.0,0.0,16.0,16.0],"texture":"#0"},"down":{"uv":[0.0,0.0,16.0,16.0],"texture":"#1"}}},{"from":[9.977,3.163,9.186],"to":[10.768,3.954,9.977],"faces":{"east":{"uv":[0.0,0.0,16.0,16.0],"texture":"#0"},"south":{"uv":[0.0,0.0,16.0,16.0],"texture":"#0"},"up":{"uv":[0.0,0.0,16.0,16.0],"texture":"#0"},"down":{"uv":[0.0,0.0,16.0,16.0],"texture":"#1"}}},{"from":[9.186,3.163,9.977],"to":[9.977,3.954,10.768],"faces":{"east":{"uv":[0.0,0.0,16.0,16.0],"texture":"#0"},"south":{"uv":[0.0,0.0,16.0,16.0],"texture":"#0"},"up":{"uv":[0.0,0.0,16.0,16.0],"texture":"#0"},"down":{"uv":[0.0,0.0,16.0,16.0],"texture":"#1"}}},{"from":[7.605,0.791,7.605],"to":[8.395,1.582,8.395],"faces":{"north":{"uv":[0.0,0.0,16.0,16.0],"texture":"#2"},"east":{"uv":[0.0,0.0,16.0,16.0],"texture":"#2"},"south":{"uv":[0.0,0.0,16.0,16.0],"texture":"#2"},"west":{"uv":[0.0,0.0,16.0,16.0],"texture":"#2"}}},{"from":[6.023,3.163,6.023],"to":[6.814,3.954,6.814],"faces":{"up":{"uv":[0.0,0.0,16.0,16.0],"texture":"#0"},"down":{"uv":[0.0,0.0,16.0,16.0],"texture":"#1"}}},{"from":[5.232,3.163,6.023],"to":[6.023,3.954,6.814],"faces":{"north":{"uv":[0.0,0.0,16.0,16.0],"texture":"#0"},"west":{"uv":[0.0,0.0,16.0,16.0],"texture":"#0"},"up":{"uv":[0.0,0.0,16.0,16.0],"texture":"#0"},"down":{"uv":[0.0,0.0,16.0,16.0],"texture":"#1"}}},{"from":[6.814,3.163,6.023],"to":[7.605,3.954,6.814],"faces":{"up":{"uv":[0.0,0.0,16.0,16.0],"texture":"#0"},"down":{"uv":[0.0,0.0,16.0,16.0],"texture":"#1"}}},{"from":[6.023,3.163,5.232],"to":[6.814,3.954,6.023],"faces":{"north":{"uv":[0.0,0.0,16.0,16.0],"texture":"#0"},"west":{"uv":[0.0,0.0,16.0,16.0],"texture":"#0"},"up":{"uv":[0.0,0.0,16.0,16.0],"texture":"#0"},"down":{"uv":[0.0,0.0,16.0,16.0],"texture":"#1"}}},{"from":[6.023,3.163,6.814],"to":[6.814,3.954,7.605],"faces":{"up":{"uv":[0.0,0.0,16.0,16.0],"texture":"#0"},"down":{"uv":[0.0,0.0,16.0,16.0],"texture":"#1"}}},{"from":[7.605,3.163,6.023],"to":[8.395,3.954,6.814],"faces":{"up":{"uv":[0.0,0.0,16.0,16.0],"texture":"#0"},"down":{"uv":[0.0,0.0,16.0,16.0],"texture":"#1"}}},{"from":[6.023,3.163,7.605],"to":[6.814,3.954,8.395],"faces":{"up":{"uv":[0.0,0.0,16.0,16.0],"texture":"#0"},"down":{"uv":[0.0,0.0,16.0,16.0],"texture":"#1"}}},{"from":[5.232,3.163,6.814],"to":[6.023,3.954,7.605],"faces":{"west":{"uv":[0.0,0.0,16.0,16.0],"texture":"#0"},"up":{"uv":[0.0,0.0,16.0,16.0],"texture":"#0"},"down":{"uv":[0.0,0.0,16.0,16.0],"texture":"#1"}}},{"from":[8.395,3.163,6.023],"to":[9.186,3.954,6.814],"faces":{"up":{"uv":[0.0,0.0,16.0,16.0],"texture":"#0"},"down":{"uv":[0.0,0.0,16.0,16.0],"texture":"#1"}}},{"from":[6.814,3.163,5.232],"to":[7.605,3.954,6.023],"faces":{"north":{"uv":[0.0,0.0,16.0,16.0],"texture":"#0"},"up":{"uv":[0.0,0.0,16.0,16.0],"texture":"#0"},"down":{"uv":[0.0,0.0,16.0,16.0],"texture":"#1"}}},{"from":[6.814,3.163,6.814],"to":[7.605,3.954,7.605],"faces":{"up":{"uv":[0.0,0.0,16.0,16.0],"texture":"#0"},"down":{"uv":[0.0,0.0,16.0,16.0],"texture":"#1"}}},{"from":[6.023,3.163,8.395],"to":[6.814,3.954,9.186],"faces":{"up":{"uv":[0.0,0.0,16.0,16.0],"texture":"#0"},"down":{"uv":[0.0,0.0,16.0,16.0],"texture":"#1"}}},{"from":[9.186,3.163,6.023],"to":[9.977,3.954,6.814],"faces":{"up":{"uv":[0.0,0.0,16.0,16.0],"texture":"#0"},"down":{"uv":[0.0,0.0,16.0,16.0],"texture":"#1"}}},{"from":[6.023,3.163,9.186],"to":[6.814,3.954,9.977],"faces":{"up":{"uv":[0.0,0.0,16.0,16.0],"texture":"#0"},"down":{"uv":[0.0,0.0,16.0,16.0],"texture":"#1"}}},{"from":[5.232,3.163,7.605],"to":[6.023,3.954,8.395],"faces":{"west":{"uv":[0.0,0.0,16.0,16.0],"texture":"#0"},"up":{"uv":[0.0,0.0,16.0,16.0],"texture":"#0"},"down":{"uv":[0.0,0.0,16.0,16.0],"texture":"#1"}}},{"from":[9.977,3.163,6.023],"to":[10.768,3.954,6.814],"faces":{"north":{"uv":[0.0,0.0,16.0,16.0],"texture":"#0"},"east":{"uv":[0.0,0.0,16.0,16.0],"texture":"#0"},"up":{"uv":[0.0,0.0,16.0,16.0],"texture":"#0"},"down":{"uv":[0.0,0.0,16.0,16.0],"texture":"#1"}}},{"from":[7.605,3.163,6.814],"to":[8.395,3.954,7.605],"faces":{"up":{"uv":[0.0,0.0,16.0,16.0],"texture":"#0"},"down":{"uv":[0.0,0.0,16.0,16.0],"texture":"#1"}}},{"from":[7.605,3.163,5.232],"to":[8.395,3.954,6.023],"faces":{"north":{"uv":[0.0,0.0,16.0,16.0],"texture":"#0"},"up":{"uv":[0.0,0.0,16.0,16.0],"texture":"#0"},"down":{"uv":[0.0,0.0,16.0,16.0],"texture":"#1"}}},{"from":[6.814,3.163,7.605],"to":[7.605,3.954,8.395],"faces":{"up":{"uv":[0.0,0.0,16.0,16.0],"texture":"#0"},"down":{"uv":[0.0,0.0,16.0,16.0],"texture":"#1"}}},{"from":[6.023,3.163,9.977],"to":[6.814,3.954,10.768],"faces":{"south":{"uv":[0.0,0.0,16.0,16.0],"texture":"#0"},"west":{"uv":[0.0,0.0,16.0,16.0],"texture":"#0"},"up":{"uv":[0.0,0.0,16.0,16.0],"texture":"#0"},"down":{"uv":[0.0,0.0,16.0,16.0],"texture":"#1"}}}]}